abstract_factories/__init__.py
abstract_factories/constants.py
abstract_factories/core.py
abstract_factories/utils.py
abstract_factories-0.4.4.dist-info/METADATA
abstract_factories-0.4.4.dist-info/WHEEL
abstract_factories-0.4.4.dist-info/top_level.txt
abstract_factories-0.4.4.dist-info/RECORD
