Metadata-Version: 2.1
Name: abstract_factories
Version: 0.4.4
Summary: Abstract Factory design pattern classes for scalable data in dynamic environments.
Home-page: https://github.com/ldunham1/abstract_factories
Author: Lee Dunham
Author-email: leedunham@gmail.com
License: MIT
Classifier: Intended Audience :: Developers
Classifier: License :: OSI Approved :: MIT License
Classifier: Programming Language :: Python
Classifier: Programming Language :: Python :: 2.7
Classifier: Programming Language :: Python :: 3
Classifier: Operating System :: OS Independent
Classifier: Topic :: Software Development :: Libraries :: Python Modules
Classifier: Topic :: Utilities
